excelutils/__init__.py
excelutils/exporter.py
save_to_excel-0.1.0.dist-info/METADATA
save_to_excel-0.1.0.dist-info/WHEEL
save_to_excel-0.1.0.dist-info/top_level.txt
save_to_excel-0.1.0.dist-info/RECORD
