Metadata-Version: 2.1
Name: save-to-excel
Version: 0.1.0
Summary: Save MongoDB or list data to Excel using pandas
Author: Your Name
Author-email: your@email.com
Requires-Python: >=3.7
Requires-Dist: pandas
Requires-Dist: openpyxl
